LICENSE
README.md
setup.py
cohesity_sdk/__init__.py
cohesity_sdk.egg-info/PKG-INFO
cohesity_sdk.egg-info/SOURCES.txt
cohesity_sdk.egg-info/dependency_links.txt
cohesity_sdk.egg-info/requires.txt
cohesity_sdk.egg-info/top_level.txt
cohesity_sdk/cluster/__init__.py
cohesity_sdk/cluster/api_client.py
cohesity_sdk/cluster/cluster_client.py
cohesity_sdk/cluster/configuration.py
cohesity_sdk/cluster/exceptions.py
cohesity_sdk/cluster/model_utils.py
cohesity_sdk/cluster/rest.py
cohesity_sdk/cluster/api/__init__.py
cohesity_sdk/cluster/api/access_token.py
cohesity_sdk/cluster/api/active_directory.py
cohesity_sdk/cluster/api/agent.py
cohesity_sdk/cluster/api/alert.py
cohesity_sdk/cluster/api/antivirus_service.py
cohesity_sdk/cluster/api/audit_log.py
cohesity_sdk/cluster/api/cloud_retrieve_task.py
cohesity_sdk/cluster/api/connectors.py
cohesity_sdk/cluster/api/d_maa_s_tenant_certificate.py
cohesity_sdk/cluster/api/data_tiering.py
cohesity_sdk/cluster/api/external_connection.py
cohesity_sdk/cluster/api/external_target.py
cohesity_sdk/cluster/api/failover.py
cohesity_sdk/cluster/api/firewall.py
cohesity_sdk/cluster/api/fleet_instance.py
cohesity_sdk/cluster/api/helios_on_prem.py
cohesity_sdk/cluster/api/identity_provider.py
cohesity_sdk/cluster/api/indexing_cloud_config.py
cohesity_sdk/cluster/api/internal.py
cohesity_sdk/cluster/api/ips.py
cohesity_sdk/cluster/api/kerberos_provider.py
cohesity_sdk/cluster/api/key_management_system.py
cohesity_sdk/cluster/api/keystone.py
cohesity_sdk/cluster/api/ldap.py
cohesity_sdk/cluster/api/marketplace_app.py
cohesity_sdk/cluster/api/mfa.py
cohesity_sdk/cluster/api/network_information_service.py
cohesity_sdk/cluster/api/network_reset.py
cohesity_sdk/cluster/api/node_group.py
cohesity_sdk/cluster/api/object.py
cohesity_sdk/cluster/api/patch_management.py
cohesity_sdk/cluster/api/platform.py
cohesity_sdk/cluster/api/policy.py
cohesity_sdk/cluster/api/privilege.py
cohesity_sdk/cluster/api/protected_object.py
cohesity_sdk/cluster/api/protection_group.py
cohesity_sdk/cluster/api/recovery.py
cohesity_sdk/cluster/api/registration.py
cohesity_sdk/cluster/api/remote_clusters.py
cohesity_sdk/cluster/api/remote_storage.py
