Metadata-Version: 2.1
Name: cohesity-sdk
Version: 1.1.0
Summary: This SDK provides operations for interfacing with the Cohesity Cluster.
Home-page: UNKNOWN
Author: Cohesity
Author-email: cohesity-api-sdks@cohesity.com
License: UNKNOWN
Platform: UNKNOWN
Requires-Python: >=3.6
License-File: LICENSE
